{
  "title": "Patient Mood Scores",
  "import_script": "<script src=\"https://cdn.jsdelivr.net/npm/d3@7\"></script>",
  "source_data": {
    "width": 700,
    "height": 740,
    "background": "#f5f1f0",
    "fontFamily": "Arial, Helvetica, sans-serif",
    "data": [
      {
        "month": "2023-01",
        "waitingArea": 4.2,
        "corridor": 3.8
      },
      {
        "month": "2023-02",
        "waitingArea": 4.5,
        "corridor": 4.1
      },
      {
        "month": "2023-03",
        "waitingArea": 5.1,
        "corridor": 4.7
      },
      {
        "month": "2023-04",
        "waitingArea": 5.8,
        "corridor": 5.3
      },
      {
        "month": "2023-05",
        "waitingArea": 6.2,
        "corridor": 5.9
      },
      {
        "month": "2023-06",
        "waitingArea": 6.7,
        "corridor": 6.3
      },
      {
        "month": "2023-07",
        "waitingArea": 7.1,
        "corridor": 6.8
      },
      {
        "month": "2023-08",
        "waitingArea": 7.5,
        "corridor": 7.2
      },
      {
        "month": "2023-09",
        "waitingArea": 7.9,
        "corridor": 7.6
      },
      {
        "month": "2023-10",
        "waitingArea": 8.3,
        "corridor": 8
      },
      {
        "month": "2023-11",
        "waitingArea": 8.6,
        "corridor": 8.3
      },
      {
        "month": "2023-12",
        "waitingArea": 8.9,
        "corridor": 8.6
      }
    ],
    "text": {
      "leftLegend": "Waiting Area",
      "rightLegend": "Corridor",
      "titleLine1": "Patient Mood Scores Rise After",
      "titleLine2": "Public Art Installation",
      "subtitleLine1": "Average mood scores improve consistently in waiting areas and",
      "subtitleLine2": "corridors through 2023 following public art installations."
    },
    "layout": {
      "chartTop": 135,
      "chartLeftPadding": 70,
      "chartRightPadding": 70,
      "centerGap": 52,
      "barHeight": 25,
      "rowGap": 11,
      "maxBarWidth": 190,
      "leftLegendX": 185,
      "rightLegendX": 460,
      "legendY": 72,
      "legendBoxSize": 12,
      "legendTextOffset": 18,
      "monthLabelYOffset": 18,
      "valueLabelOffset": 8,
      "titleY": 600,
      "subtitleY": 678
    },
    "styles": {
      "leftBar": {
        "fill": "#C95F54"
      },
      "rightBar": {
        "fill": "#F0C65E"
      },
      "legend": {
        "textFill": "#333333",
        "fontSize": "16px",
        "fontWeight": 400
      },
      "monthLabel": {
        "fill": "#333333",
        "fontSize": "14px",
        "fontWeight": 400
      },
      "valueLabel": {
        "fill": "#333333",
        "fontSize": "14px",
        "fontWeight": 400
      },
      "title": {
        "fill": "#444444",
        "fontSize": "30px",
        "fontWeight": 700,
        "lineHeight": 34
      },
      "subtitle": {
        "fill": "#444444",
        "fontSize": "14px",
        "fontWeight": 400,
        "lineHeight": 20
      }
    }
  },
  "render_script": [
    "d3.select(\"body\")",
    "  .style(\"margin\", \"0\")",
    "  .style(\"font-family\", source_data.fontFamily)",
    "  .style(\"display\", \"flex\")",
    "  .style(\"justify-content\", \"center\")",
    "  .style(\"align-items\", \"flex-start\");",
    "",
    "const svg = d3.select(\"body\")",
    "  .append(\"svg\")",
    "  .attr(\"width\", source_data.width)",
    "  .attr(\"height\", source_data.height)",
    "  .attr(\"viewBox\", `0 0 ${source_data.width} ${source_data.height}`);",
    "",
    "svg.append(\"rect\")",
    "  .attr(\"x\", 0)",
    "  .attr(\"y\", 0)",
    "  .attr(\"width\", source_data.width)",
    "  .attr(\"height\", source_data.height)",
    "  .attr(\"fill\", source_data.background);",
    "",
    "const { width, data, text, layout, styles } = source_data;",
    "const centerX = width / 2;",
    "const leftBarEndX = centerX - layout.centerGap / 2;",
    "const rightBarStartX = centerX + layout.centerGap / 2;",
    "const maxValue = d3.max(data, (d) => Math.max(d.waitingArea, d.corridor));",
    "const xScale = d3.scaleLinear().domain([0, maxValue]).range([0, layout.maxBarWidth]);",
    "",
    "const legendGroup = svg.append(\"g\");",
    "legendGroup",
    "  .append(\"rect\")",
    "  .attr(\"x\", layout.leftLegendX)",
    "  .attr(\"y\", layout.legendY)",
    "  .attr(\"width\", layout.legendBoxSize)",
    "  .attr(\"height\", layout.legendBoxSize)",
    "  .attr(\"fill\", styles.leftBar.fill);",
    "legendGroup",
    "  .append(\"text\")",
    "  .attr(\"x\", layout.leftLegendX + layout.legendTextOffset)",
    "  .attr(\"y\", layout.legendY + layout.legendBoxSize - 1)",
    "  .attr(\"fill\", styles.legend.textFill)",
    "  .style(\"font-size\", styles.legend.fontSize)",
    "  .style(\"font-weight\", styles.legend.fontWeight)",
    "  .text(text.leftLegend);",
    "legendGroup",
    "  .append(\"rect\")",
    "  .attr(\"x\", layout.rightLegendX)",
    "  .attr(\"y\", layout.legendY)",
    "  .attr(\"width\", layout.legendBoxSize)",
    "  .attr(\"height\", layout.legendBoxSize)",
    "  .attr(\"fill\", styles.rightBar.fill);",
    "legendGroup",
    "  .append(\"text\")",
    "  .attr(\"x\", layout.rightLegendX + layout.legendTextOffset)",
    "  .attr(\"y\", layout.legendY + layout.legendBoxSize - 1)",
    "  .attr(\"fill\", styles.legend.textFill)",
    "  .style(\"font-size\", styles.legend.fontSize)",
    "  .style(\"font-weight\", styles.legend.fontWeight)",
    "  .text(text.rightLegend);",
    "",
    "const rows = svg.append(\"g\");",
    "data.forEach((d, i) => {",
    "  const y = layout.chartTop + i * (layout.barHeight + layout.rowGap);",
    "  const leftWidth = xScale(d.waitingArea);",
    "  const rightWidth = xScale(d.corridor);",
    "  const leftX = leftBarEndX - leftWidth;",
    "",
    "  rows",
    "    .append(\"rect\")",
    "    .attr(\"x\", leftX)",
    "    .attr(\"y\", y)",
    "    .attr(\"width\", leftWidth)",
    "    .attr(\"height\", layout.barHeight)",
    "    .attr(\"fill\", styles.leftBar.fill);",
    "  rows",
    "    .append(\"rect\")",
    "    .attr(\"x\", rightBarStartX)",
    "    .attr(\"y\", y)",
    "    .attr(\"width\", rightWidth)",
    "    .attr(\"height\", layout.barHeight)",
    "    .attr(\"fill\", styles.rightBar.fill);",
    "  rows",
    "    .append(\"text\")",
    "    .attr(\"x\", leftX - layout.valueLabelOffset)",
    "    .attr(\"y\", y + layout.monthLabelYOffset)",
    "    .attr(\"text-anchor\", \"end\")",
    "    .attr(\"fill\", styles.valueLabel.fill)",
    "    .style(\"font-size\", styles.valueLabel.fontSize)",
    "    .style(\"font-weight\", styles.valueLabel.fontWeight)",
    "    .text(d.waitingArea % 1 === 0 ? d.waitingArea.toFixed(0) : d.waitingArea.toFixed(1));",
    "  rows",
    "    .append(\"text\")",
    "    .attr(\"x\", centerX)",
    "    .attr(\"y\", y + layout.monthLabelYOffset)",
    "    .attr(\"text-anchor\", \"middle\")",
    "    .attr(\"fill\", styles.monthLabel.fill)",
    "    .style(\"font-size\", styles.monthLabel.fontSize)",
    "    .style(\"font-weight\", styles.monthLabel.fontWeight)",
    "    .text(d.month);",
    "  rows",
    "    .append(\"text\")",
    "    .attr(\"x\", rightBarStartX + rightWidth + layout.valueLabelOffset)",
    "    .attr(\"y\", y + layout.monthLabelYOffset)",
    "    .attr(\"text-anchor\", \"start\")",
    "    .attr(\"fill\", styles.valueLabel.fill)",
    "    .style(\"font-size\", styles.valueLabel.fontSize)",
    "    .style(\"font-weight\", styles.valueLabel.fontWeight)",
    "    .text(d.corridor % 1 === 0 ? d.corridor.toFixed(0) : d.corridor.toFixed(1));",
    "});",
    "",
    "const title = svg",
    "  .append(\"text\")",
    "  .attr(\"x\", centerX)",
    "  .attr(\"y\", layout.titleY)",
    "  .attr(\"text-anchor\", \"middle\")",
    "  .attr(\"fill\", styles.title.fill)",
    "  .style(\"font-size\", styles.title.fontSize)",
    "  .style(\"font-weight\", styles.title.fontWeight);",
    "title.append(\"tspan\").attr(\"x\", centerX).attr(\"dy\", 0).text(text.titleLine1);",
    "title.append(\"tspan\").attr(\"x\", centerX).attr(\"dy\", styles.title.lineHeight).text(text.titleLine2);",
    "",
    "const subtitle = svg",
    "  .append(\"text\")",
    "  .attr(\"x\", centerX)",
    "  .attr(\"y\", layout.subtitleY)",
    "  .attr(\"text-anchor\", \"middle\")",
    "  .attr(\"fill\", styles.subtitle.fill)",
    "  .style(\"font-size\", styles.subtitle.fontSize)",
    "  .style(\"font-weight\", styles.subtitle.fontWeight);",
    "subtitle.append(\"tspan\").attr(\"x\", centerX).attr(\"dy\", 0).text(text.subtitleLine1);",
    "subtitle.append(\"tspan\").attr(\"x\", centerX).attr(\"dy\", styles.subtitle.lineHeight).text(text.subtitleLine2);"
  ]
}
